pyxbox/__init__.py
pyxbox/mail.py
pyxbox/media.py
pyxbox/proxies.py
pyxbox/tools.py
pyxbox/tools2.py
pyxbox/tools5.py
pyxbox/user_agent.py
pyxbox/weibo_utils.py
pyxbox/bilibili_utils/ApiException.py
pyxbox/bilibili_utils/BytesReader.py
pyxbox/bilibili_utils/Color.py
pyxbox/bilibili_utils/Danmaku.py
pyxbox/bilibili_utils/DanmakuClosedException.py
pyxbox/bilibili_utils/ResponseException.py
pyxbox/bilibili_utils/__init__.py
pyxbox/bilibili_utils/utils.py
pyxbox/bilibili_utils/varint.py
pyxbox-0.1.8.dist-info/LICENSE
pyxbox-0.1.8.dist-info/METADATA
pyxbox-0.1.8.dist-info/WHEEL
pyxbox-0.1.8.dist-info/top_level.txt
pyxbox-0.1.8.dist-info/RECORD
