Metadata-Version: 2.1
Name: pyxbox
Version: 0.1.8
Home-page: https://gitee.com/CN-AntAI/pyxbox
Author: BruceLong
Author-email: 18656170559@163.com
License: MIT Licence
Platform: any
License-File: LICENSE
Requires-Dist: wheel
Requires-Dist: w3lib
Requires-Dist: requests
Requires-Dist: demjson (==1.6)
Requires-Dist: ffmpeg-python
Requires-Dist: tqdm
Requires-Dist: six
